trossen_aloha_ui/__init__.py
trossen_aloha_ui/__main__.py
trossen_aloha_ui/application.sh
trossen_aloha_ui/configs/calibration/aloha_default/left_follower.json
trossen_aloha_ui/configs/calibration/aloha_default/left_leader.json
trossen_aloha_ui/configs/calibration/aloha_default/right_follower.json
trossen_aloha_ui/configs/calibration/aloha_default/right_leader.json
trossen_aloha_ui/configs/robot/aloha.yaml
trossen_aloha_ui/configs/tasks.yaml
trossen_aloha_ui/post_install.py
trossen_aloha_ui/resources/__init__.py
trossen_aloha_ui/resources/aloha.png
trossen_aloha_ui/resources/aloha_gui.png
trossen_aloha_ui/resources/app.py
trossen_aloha_ui/resources/app.ui
trossen_aloha_ui/resources/no_video.jpg
trossen_aloha_ui/ui/__init__.py
trossen_aloha_ui/ui/main_window.py
trossen_aloha_ui/utils/__init__.py
trossen_aloha_ui/utils/constants.py
trossen_aloha_ui/utils/utils.py
trossen_aloha_ui/workers/__init__.py
trossen_aloha_ui/workers/recorder.py
trossen_aloha_ui/workers/yaml.py
trossen_aloha_ui-1.0.1.dist-info/LICENSE
trossen_aloha_ui-1.0.1.dist-info/METADATA
trossen_aloha_ui-1.0.1.dist-info/WHEEL
trossen_aloha_ui-1.0.1.dist-info/entry_points.txt
trossen_aloha_ui-1.0.1.dist-info/RECORD
